[
    {
        "imgRate": [],
        "productName": "Điện Thoại Xiaomi Redmi 10 4GB/128GB - Hàng Chính Hãng",
        "rating": 4,
        "satisfy": "",
        "content": "abc",
        "productImg": "https://salt.tikicdn.com/ts/product/4a/be/ec/a65c067d6c22ae48eb3ea400247c4c0d.png",
        "userId": "20b80ec5-300b-4a33-90c9-e846df058db1",
        "productId": "9fb4ca8325e34716bb4040474b1e8ff3",
        "userName": "Đông Phương Bất Bại",
        "userAvatar": "https://res.cloudinary.com/duk2lo18t/image/upload/v1660575231/tiki_avatar/0336979921.png",
        "likedList": [],
        "createdAt": 1660633882527,
        "updatedAt": 1660633882527,
        "id": "c01e50fd-c7cf-4916-9b79-95c5f4ce889c"
    },
    {
        "imgRate": [],
        "productName": "Thùng 24 Lon Nước Ngọt Có Gaz Mirinda Soda Kem Việt Quất (320ml/lon)",
        "rating": 5,
        "satisfy": "",
        "content": "wwwwwwwwwwwww",
        "productImg": "https://salt.tikicdn.com/media/catalog/producttmp/30/16/14/d56b3302aa770b287b09c35f13be19a8.PNG",
        "userId": "20b80ec5-300b-4a33-90c9-e846df058db1",
        "productId": "75ef119479bb430abf2d76c43c8ba735",
        "userName": "Đông Phương Bất Bại",
        "userAvatar": "https://res.cloudinary.com/duk2lo18t/image/upload/v1660575231/tiki_avatar/0336979921.png",
        "likedList": [],
        "createdAt": 1660633891738,
        "updatedAt": 1660633891738,
        "id": "055355cf-aa67-4d3a-8f9c-92bea3c45ea4"
    },
    {
        "imgRate": [],
        "productName": "Ổ Cứng SSD Kingston A400 (240GB) - Hàng Chính Hãng",
        "rating": 2,
        "satisfy": "",
        "content": "aaaaaaaaaaaaaaaaa",
        "productImg": "https://salt.tikicdn.com/ts/product/06/d0/00/9df3937c390fcc0b66161f4dbe783757.jpg",
        "userId": "20b80ec5-300b-4a33-90c9-e846df058db1",
        "productId": "c0000c9ba7d948f396085454db51bb6a",
        "userName": "Đông Phương Bất Bại",
        "userAvatar": "https://res.cloudinary.com/duk2lo18t/image/upload/v1660575231/tiki_avatar/0336979921.png",
        "likedList": [],
        "createdAt": 1660633900621,
        "updatedAt": 1660633900621,
        "id": "2093902a-daf3-4bbd-8fe1-099e233beeeb"
    },
    {
        "imgRate": [],
        "productName": "Tã/bỉm quần Bobby Mega Jumbo Lõi nén thần kì 3mm - Tặng 12 miếng trong gói",
        "rating": 4,
        "satisfy": "",
        "content": "eeeeê",
        "productImg": "https://salt.tikicdn.com/media/catalog/producttmp/21/1d/df/804fac7470690b3942c44bc7ac1530e0.jpg",
        "userId": "20b80ec5-300b-4a33-90c9-e846df058db1",
        "productId": "f203661ba7c94bb2891b071534d5d0aa",
        "userName": "Đông Phương Bất Bại",
        "userAvatar": "https://res.cloudinary.com/duk2lo18t/image/upload/v1660575231/tiki_avatar/0336979921.png",
        "likedList": [],
        "createdAt": 1660633910575,
        "updatedAt": 1660633910575,
        "id": "ca888689-6640-4ffd-a602-782ccf2fac0f"
    },
    {
        "imgRate": [],
        "productName": "Bàn chải nhà tắm, cọ bồn rửa Parroti Clever CR01",
        "storeName": "Tiki",
        "rating": 3,
        "satisfy": "",
        "content": "fff",
        "productImg": "https://salt.tikicdn.com/ts/product/13/fa/df/4ff5a01f99d7599c45b053aa56979f06.jpg",
        "isreviewed": "True",
        "createdAt": 1660633925930,
        "updatedAt": 1660633925930,
        "id": "fa67a102-1982-43ed-80a0-186b805a5303"
    },
    {
        "imgRate": [],
        "productName": "Dép cói, mây đan đế chống trượt đi trong nhà, trong văn phòng, trong khách sạn , freesize, màu săc họa tiết giao ngẫu nhiên",
        "storeName": "Tiki",
        "rating": 3,
        "satisfy": "",
        "content": "d",
        "productImg": "https://salt.tikicdn.com/ts/product/96/28/7c/e49e6283ee7ce5b19e7d90329f20fd4c.jpg",
        "isreviewed": "True",
        "createdAt": 1660634043219,
        "updatedAt": 1660634043219,
        "id": "6d35a715-cf3a-4b6b-a254-f866670f8477"
    },
    {
        "imgRate": [],
        "productName": "Dép cói, mây đan đế chống trượt đi trong nhà, trong văn phòng, trong khách sạn , freesize, màu săc họa tiết giao ngẫu nhiên",
        "storeName": "Tiki",
        "rating": 3,
        "satisfy": "",
        "content": "d",
        "productImg": "https://salt.tikicdn.com/ts/product/96/28/7c/e49e6283ee7ce5b19e7d90329f20fd4c.jpg",
        "isreviewed": "True",
        "createdAt": 1660634043708,
        "updatedAt": 1660634043708,
        "id": "b79f7bfd-4505-4db4-89d4-6f772ae0c955"
    }
]